tests/__init__.py
tests/test_file.py
tools3/__init__.py
tools3/base_logger.py
tools3/base_obj.py
tools3/caller.py
tools3/file.py
tools3/cli/__init__.py
tools3/cli/biz_compiler.py
tools3/cli/cli.py
tools3/cli/compiler.py
tools3/cli/func.py
tools3/cli/prompt.py
tools3/compile/__init__.py
tools3/compile/compile.py
tools3/compile/codep/__init__.py
tools3/compile/codep/php_parser.py
tools3/compile/config/__init__.py
tools3/compile/config/fields_json_config.py
tools3/compile/config/params_json_config.py
tools3/compile/py/__init__.py
tools3/compile/py/jc_compile_py.py
tools3/compile/py/json_config_compile_py.py
tools3/compile/uc/__init__.py
tools3/compile/uc/compile_uc.py
tools3/compile/uc/func.py
tools3/compile/uc/jc_compile_uc.py
tools3/compile/uc/json_config_compile_uc.py
tools3/compile/uc/py_compil_uc.py
tools3/compile/uc/uc_gen.py
tools3/compile/uc/uc_gen1.py
tools3/compile/utc/__init__.py
tools3/compile/utc/uc_compile_go.py
tools3/compile/utc/uc_compile_phpunit.py
tools3/compile/utc/uc_compile_utc.py
tools3/data/php-al/PhpFileParser.php
tools3/data/php-al/README.md
tools3/data/php-al/composer.json
tools3/data/php-al/composer.lock
tools3/data/php-al/composer.phar
tools3/data/php-al/prompt.md
tools3/data/php-al/vendor/autoload.php
tools3/data/php-al/vendor/bin/php-parse
tools3/data/php-al/vendor/composer/ClassLoader.php
tools3/data/php-al/vendor/composer/LICENSE
tools3/data/php-al/vendor/composer/autoload_classmap.php
tools3/data/php-al/vendor/composer/autoload_namespaces.php
tools3/data/php-al/vendor/composer/autoload_psr4.php
tools3/data/php-al/vendor/composer/autoload_real.php
tools3/data/php-al/vendor/composer/autoload_static.php
tools3/data/php-al/vendor/composer/installed.json
tools3/data/php-al/vendor/nikic/php-parser/LICENSE
tools3/data/php-al/vendor/nikic/php-parser/README.md
tools3/data/php-al/vendor/nikic/php-parser/composer.json
tools3/data/php-al/vendor/nikic/php-parser/bin/php-parse
tools3/data/php-al/vendor/nikic/php-parser/lib/PhpParser/Builder.php
tools3-0.1.1.dist-info/METADATA
tools3-0.1.1.dist-info/WHEEL
tools3-0.1.1.dist-info/entry_points.txt
tools3-0.1.1.dist-info/top_level.txt
tools3-0.1.1.dist-info/RECORD
