Metadata-Version: 2.1
Name: tools3
Version: 0.1.1
Summary: develop tools
Home-page: https://github.com/qq1060656096
Author: qq1060656096
Author-email: 1060656096@qq.com
Classifier: Programming Language :: Python :: 3
Classifier: License :: OSI Approved :: MIT License
Classifier: Operating System :: OS Independent
Requires-Python: >=3.10
Requires-Dist: loguru==0.7.3
Requires-Dist: langchain-community==0.3.19
Requires-Dist: langchain-core==0.3.43
Requires-Dist: langchain-ollama==0.2.3
Requires-Dist: langchain-openai==0.2.14
